setup.py
herbert/__init__.py
herbert/ast.py
herbert/interpreter.py
herbert/lexer.py
herbert/main.py
herbert/parser.py
herbert.egg-info/PKG-INFO
herbert.egg-info/SOURCES.txt
herbert.egg-info/dependency_links.txt
herbert.egg-info/entry_points.txt
herbert.egg-info/not-zip-safe
herbert.egg-info/requires.txt
herbert.egg-info/top_level.txt