Metadata-Version: 1.1
Name: herbert
Version: 0.2
Summary: An implmentation of herbert language
Home-page: UNKNOWN
Author: Sebastian Pawluś
Author-email: sebastian.pawlus@gmail.com
License: UNKNOWN
Platform: UNKNOWN
Classifier: License :: OSI Approved :: BSD License
Classifier: Programming Language :: Python
